notify/__init__.py
notify/exceptions.py
notify/collections/__init__.py
notify/collections/_dict.py
notify/collections/_list.py
notify/collections/tests/__init__.py
notify/collections/tests/test_dict.py
notify/collections/tests/test_list.py
notify/property/__init__.py
notify/property/_property.py
notify/property/test_property.py
notify/signal/__init__.py
notify/signal/_connection.py
notify/signal/_signature.py
notify/signal/backends.py
notify/signal/signal.py
notify/signal/tests/__init__.py
notify/signal/tests/conftest.py
notify/signal/tests/test_signal.py
python_notify-1.0.1.dist-info/LICENSE
python_notify-1.0.1.dist-info/METADATA
python_notify-1.0.1.dist-info/WHEEL
python_notify-1.0.1.dist-info/top_level.txt
python_notify-1.0.1.dist-info/RECORD
