Metadata-Version: 2.1
Name: python-notify
Version: 1.0.1
Summary: Implementation of observer design pattern in python3
Home-page: https://github.com/DanilaKorobkov/python-notify
Author: DanilaKorobkov
Author-email: korobkov.danila.yurevich@gmail.com
License: UNKNOWN
Keywords: observer signal slots notify publish subscriber notifiable_property
Platform: UNKNOWN
